odoo/addons/agreement_legal_sale_fieldservice/README.rst
odoo/addons/agreement_legal_sale_fieldservice/__init__.py
odoo/addons/agreement_legal_sale_fieldservice/__manifest__.py
odoo/addons/agreement_legal_sale_fieldservice/i18n/agreement_legal_sale_fieldservice.pot
odoo/addons/agreement_legal_sale_fieldservice/i18n/ca.po
odoo/addons/agreement_legal_sale_fieldservice/i18n/es.po
odoo/addons/agreement_legal_sale_fieldservice/i18n/pt_BR.po
odoo/addons/agreement_legal_sale_fieldservice/models/__init__.py
odoo/addons/agreement_legal_sale_fieldservice/models/sale_order.py
odoo/addons/agreement_legal_sale_fieldservice/readme/CONTRIBUTORS.rst
odoo/addons/agreement_legal_sale_fieldservice/readme/CREDITS.rst
odoo/addons/agreement_legal_sale_fieldservice/readme/DESCRIPTION.rst
odoo/addons/agreement_legal_sale_fieldservice/readme/ROADMAP.rst
odoo/addons/agreement_legal_sale_fieldservice/readme/USAGE.rst
odoo/addons/agreement_legal_sale_fieldservice/static/description/icon.png
odoo/addons/agreement_legal_sale_fieldservice/static/description/index.html
odoo12_addon_agreement_legal_sale_fieldservice-12.0.1.0.0.99.dev15.dist-info/METADATA
odoo12_addon_agreement_legal_sale_fieldservice-12.0.1.0.0.99.dev15.dist-info/WHEEL
odoo12_addon_agreement_legal_sale_fieldservice-12.0.1.0.0.99.dev15.dist-info/top_level.txt
odoo12_addon_agreement_legal_sale_fieldservice-12.0.1.0.0.99.dev15.dist-info/RECORD
