Metadata-Version: 2.1
Name: odoo12-addon-agreement-legal-sale-fieldservice
Version: 12.0.1.0.0.99.dev15
Summary: Create an agreement when the sale order is confirmed
Home-page: https://github.com/OCA/contract
Author: Open Source Integrators, Odoo Community Association (OCA)
Author-email: support@odoo-community.org
License: AGPL-3
Platform: UNKNOWN
Classifier: Programming Language :: Python
Classifier: Framework :: Odoo
Classifier: Framework :: Odoo :: 12.0
Classifier: License :: OSI Approved :: GNU Affero General Public License v3
Classifier: Development Status :: 4 - Beta
Requires-Python: >=3.5
Requires-Dist: odoo12-addon-agreement-legal-sale
Requires-Dist: odoo12-addon-fieldservice-agreement
Requires-Dist: odoo12-addon-fieldservice-sale
Requires-Dist: odoo <12.1dev,>=12.0a
